Metadata-Version: 1.0
Name: fullhistory
Version: 0.3.1
Summary: Fullhistory for Django
Home-page: https://github.com/cuker/django-fullhistory
Author: Jason Kraus
Author-email: zbyte64@gmail.com
License: UNKNOWN
Keywords: django history
Platform: UNKNOWN
Classifier: Programming Language :: Python
Classifier: Operating System :: OS Independent
Classifier: Natural Language :: English
Classifier: Development Status :: 4 - Beta
Classifier: Intended Audience :: Developers
Classifier: Topic :: Internet :: WWW/HTTP :: Dynamic Content
